swancontents/__init__.py
swancontents/_version.py
swancontents/checkpoints/__init__.py
swancontents/checkpoints/eoscheckpoints.py
swancontents/filemanager/__init__.py
swancontents/filemanager/proj_url_checker.py
swancontents/filemanager/projects_mixin.py
swancontents/filemanager/swan_eos_filemanager.py
swancontents/filemanager/eos/__init__.py
swancontents/filemanager/eos/fileio.py
swancontents/filemanager/eos/handlers.py
swancontents/serverextension/__init__.py
swancontents/serverextension/handlers/__init__.py
swancontents/serverextension/handlers/download.py
swancontents/serverextension/templates/404.html
swancontents/serverextension/templates/download.html
swancontents/serverextension/templates/nbextensions_configurator.html
swancontents/serverextension/templates/page.html
swancontents/swanclassic/__init__.py
swancontents/swanclassic/notebookapp.py
swancontents/swanclassic/handlers/__init__.py
swancontents/swanclassic/handlers/cernbox.py
swancontents/swanclassic/handlers/notebookviewer.py
swancontents/swanclassic/handlers/projects.py
swancontents/swanclassic/handlers/share.py
swancontents/swanclassic/labextension/package.json
swancontents/swanclassic/labextension/schemas/@swanclassic/lab-extension/interface-switcher.json
swancontents/swanclassic/labextension/schemas/@swanclassic/lab-extension/launch-tree.json
swancontents/swanclassic/labextension/schemas/@swanclassic/lab-extension/package.json.orig
swancontents/swanclassic/labextension/static/381.c95740831649a7091f6c.js
swancontents/swanclassic/labextension/static/568.29bacd0377bae5b41d33.js
swancontents/swanclassic/labextension/static/747.7bcf389ea10665b0fb15.js
swancontents/swanclassic/labextension/static/remoteEntry.fda90815f442b9c35952.js
swancontents/swanclassic/labextension/static/style.js
swancontents/swanclassic/labextension/static/third-party-licenses.json
swancontents/swanclassic/static/swan/js/contents.js
swancontents/swanclassic/static/swan/js/notebooklist.js
swancontents-2.1.15.dist-info/METADATA
swancontents-2.1.15.dist-info/WHEEL
swancontents-2.1.15.dist-info/entry_points.txt
swancontents-2.1.15.dist-info/top_level.txt
swancontents-2.1.15.dist-info/RECORD
